gtfobinsuid.py
gtfobinsuid-1.3.0.dist-info/licenses/LICENSE.bak
gtfobinsuid-1.3.0.dist-info/METADATA
gtfobinsuid-1.3.0.dist-info/WHEEL
gtfobinsuid-1.3.0.dist-info/entry_points.txt
gtfobinsuid-1.3.0.dist-info/top_level.txt
gtfobinsuid-1.3.0.dist-info/RECORD
