Metadata-Version: 2.4
Name: gtfobinsuid
Version: 1.3.0
Summary: A Python tool for automating SUID/SGID binary enumeration against GTFOBins
Author-email: strikoder <strikoder@gmail.com>
Project-URL: Homepage, https://github.com/strikoder/gtfobinSUID
Project-URL: Bug Tracker, https://github.com/strikoder/gtfobinSUID/issues
Project-URL: Repository, https://github.com/strikoder/gtfobinSUID
Project-URL: Documentation, https://github.com/strikoder/gtfobinSUID#readme
Keywords: suid,gtfobins,security,penetration-testing,privilege-escalation,enumeration,pentest
Classifier: Development Status :: 4 - Beta
Classifier: Intended Audience :: Information Technology
Classifier: Intended Audience :: System Administrators
Classifier: Topic :: Security
Classifier: Topic :: System :: Systems Administration
Classifier: License :: OSI Approved :: GNU General Public License v3 (GPLv3)
Classifier: Programming Language :: Python :: 3
Classifier: Programming Language :: Python :: 3.6
Classifier: Programming Language :: Python :: 3.7
Classifier: Programming Language :: Python :: 3.8
Classifier: Programming Language :: Python :: 3.9
Classifier: Programming Language :: Python :: 3.10
Classifier: Programming Language :: Python :: 3.11
Classifier: Programming Language :: Python :: 3.12
Classifier: Operating System :: POSIX :: Linux
Classifier: Operating System :: MacOS
Classifier: Operating System :: Microsoft :: Windows
Requires-Python: >=3.6
License-File: LICENSE.bak
Requires-Dist: requests>=2.25.0
Requires-Dist: beautifulsoup4>=4.9.0
Dynamic: license-file
